keccelsms/__init__.py
pykeccelsms-0.2.dist-info/METADATA
pykeccelsms-0.2.dist-info/WHEEL
pykeccelsms-0.2.dist-info/top_level.txt
pykeccelsms-0.2.dist-info/RECORD
